__init__.py
multivalidator/__init__.py
multivalidator/bank_card.py
multivalidator/cnpj.py
multivalidator/cpf.py
multivalidator/date.py
multivalidator/emails.py
multivalidator/fake_data.py
multivalidator/fone_number.py
multivalidator/passport.py
multivalidator/password.py
multivalidator/url.py
multi_validator_generator-0.0.8.dist-info/LICENSE
multi_validator_generator-0.0.8.dist-info/METADATA
multi_validator_generator-0.0.8.dist-info/WHEEL
multi_validator_generator-0.0.8.dist-info/top_level.txt
multi_validator_generator-0.0.8.dist-info/RECORD
