Metadata-Version: 2.1
Name: multi-validator-generator
Version: 0.0.8
Summary: Um pacote para validar diverso tipos de dados e documentos
Home-page: https://github.com/JoaoVitorMoreiraPassos/Multi_validator
License-File: LICENSE
